{
    "name": "Social Network Testnet",
    "chain": "EARTHTEST",
    "rpc": ["https://testnet-rpc.social.network"],
    "faucets": [],
    "nativeCurrency": {
      "name": "tBTC",
      "symbol": "tBTC",
      "decimals": 18
    },
    "infoURL": "https://social.network",
    "shortName": "earthtest",
    "chainId": 749,
    "networkId": 749,
    "slip44": 60,
    "icon": "earthtest",
    "explorers": [
      {
        "name": "Social Network Explorer",
        "url": "https://testnet.social.network",
        "standard": "none"
      }
    ]
}
