{
  "name": "AnchorChain Testnet",
  "chain": "ANCH",
  "rpc": [
    "https://api-testnet.anchorchain.co.za/rpc"
  ],
  "faucets": [
    "https://api-testnet.anchorchain.co.za/v1/faucet/claim"
  ],
  "nativeCurrency": {
    "name": "Anchor",
    "symbol": "ANCH",
    "decimals": 18
  },
  "infoURL": "https://anchorchain.co.za",
  "shortName": "anch-testnet",
  "chainId": 7605,
  "networkId": 7605,
  "testnet": true,
  "explorers": [
    {
      "name": "AnchorChain Testnet Explorer",
      "url": "https://explorer-testnet.anchorchain.co.za",
      "standard": "none"
    }
  ]
}
