{
  "name": "GoHeal Mainnet",
  "chain": "GoHeal",
  "rpc": ["https://rpc.gohchain.com"],
  "faucets": [],
  "nativeCurrency": {
    "name": "GoHeal",
    "symbol": "GOH",
    "decimals": 18
  },

  "infoURL": "https://explorer.gohchain.com",
  "shortName": "goh",
  "chainId": 3901,
  "networkId": 3901,
  "icon": "goheal",
  "explorers": [
    {
      "name": "GoHeal Mainnet Explorer",
      "url": "https://explorer.gohchain.com/",
      "icon": "goheal",
      "standard": "EIP3091"
    }
  ]
}
