{
  "name": "Gitshock Chain Testnet",
  "chain": "Gitshock Cartenz",
  "icon": "gitshockchain",
  "rpc": [
    "https://rpc.cartenz.works",
    "https://rpc-us.cartenz.works"
  ],
  "faucets": [
    "https://testnet-faucet.gitshock.com"
  ],
  "nativeCurrency": {
    "name": "Gitshock",
    "symbol": "GTFX",
    "decimals": 18
  },
  "features": [
    {
      "name": "EIP155"
    },
    {
      "name": "EIP1559"
    },
    {
      "name": "EIP1898"
    }
  ],
  "infoURL": "https://gitshock.com",
  "shortName": "gtfx",
  "chainId": 1881,
  "networkId": 1881,
  "explorers": [
    {
      "name": "blockscout",
      "url": "https://scan.cartenz.works",
      "icon": "gitshockscan",
      "standard": "none"
    }
  ]
}
