{
  "name": "Blockton Blockchain",
  "chain": "Blockton Blockchain",
  "icon": "bton",
  "rpc": ["https://rpc.blocktonscan.com/"],
  "faucets": ["https://faucet.blocktonscan.com/"],
  "nativeCurrency": {
    "name": "BLOCKTON",
    "symbol": "BTON",
    "decimals": 18
  },
  "infoURL": "https://blocktoncoin.com",
  "shortName": "BTON",
  "chainId": 8272,
  "networkId": 8272,
  "explorers": [
    {
      "name": "Blockton Explorer",
      "url": "https://blocktonscan.com",
      "standard": "none"
    }
  ]
}
