{
  "name": "PandaSea Testnet",
  "chain": "PandaSea Testnet",
  "rpc": ["https://rpc.testnet.pandasea.io"],
  "faucets": ["https://faucet.pandasea.io"],
  "nativeCurrency": {
    "name": "PandaSea Coin",
    "symbol": "PANDA",
    "decimals": 18
  },
  "infoURL": "https://test.pandaseascan.com",
  "shortName": "Pandasea-Testnet",
  "chainId": 7770,
  "networkId": 7770,
  "explorers": [
    {
      "name": "tracehawk",
      "url": "https://test.pandaseascan.com",
      "standard": "none"
    }
  ]
}
